setup.py
odoo/addons/opencell_somconnexio/CHANGELOG.md
odoo/addons/opencell_somconnexio/README.rst
odoo/addons/opencell_somconnexio/__init__.py
odoo/addons/opencell_somconnexio/__manifest__.py
odoo/addons/opencell_somconnexio/controllers/__init__.py
odoo/addons/opencell_somconnexio/controllers/controllers.py
odoo/addons/opencell_somconnexio/data/ir_config_parameter.xml
odoo/addons/opencell_somconnexio/i18n/ca_ES.po
odoo/addons/opencell_somconnexio/i18n/es.po
odoo/addons/opencell_somconnexio/listeners/__init__.py
odoo/addons/opencell_somconnexio/listeners/contract_line_listener.py
odoo/addons/opencell_somconnexio/listeners/contract_listener.py
odoo/addons/opencell_somconnexio/listeners/res_partner_listener.py
odoo/addons/opencell_somconnexio/listeners/service_contract_info_listener.py
odoo/addons/opencell_somconnexio/models/__init__.py
odoo/addons/opencell_somconnexio/models/contract.py
odoo/addons/opencell_somconnexio/models/opencell_configuration.py
odoo/addons/opencell_somconnexio/models/res_partner.py
odoo/addons/opencell_somconnexio/opencell_models/__init__.py
odoo/addons/opencell_somconnexio/opencell_models/access.py
odoo/addons/opencell_somconnexio/opencell_models/account_hierarchy_resource.py
odoo/addons/opencell_somconnexio/opencell_models/crm_account_hierarchy.py
odoo/addons/opencell_somconnexio/opencell_models/customer.py
odoo/addons/opencell_somconnexio/opencell_models/opencell_resource.py
odoo/addons/opencell_somconnexio/opencell_models/services.py
odoo/addons/opencell_somconnexio/opencell_models/subscription.py
odoo/addons/opencell_somconnexio/opencell_models/opencell_types/__init__.py
odoo/addons/opencell_somconnexio/opencell_models/opencell_types/address.py
odoo/addons/opencell_somconnexio/opencell_models/opencell_types/custom_field.py
odoo/addons/opencell_somconnexio/opencell_models/opencell_types/description.py
odoo/addons/opencell_somconnexio/opencell_services/__init__.py
odoo/addons/opencell_somconnexio/opencell_services/access_service.py
odoo_addon_opencell_somconnexio.egg-info/PKG-INFO
odoo_addon_opencell_somconnexio.egg-info/SOURCES.txt
odoo_addon_opencell_somconnexio.egg-info/dependency_links.txt
odoo_addon_opencell_somconnexio.egg-info/not-zip-safe
odoo_addon_opencell_somconnexio.egg-info/requires.txt
odoo_addon_opencell_somconnexio.egg-info/top_level.txt