Metadata-Version: 2.4
Name: odoo-addon-opencell_somconnexio
Version: 16.0.1.1.0
Summary: Synchronize the needed objects to invoicing from OpenCell.
Home-page: https://git.coopdevs.org/coopdevs/som-connexio/odoo/odoo-somconnexio
Author: Som Connexió SCCL, Coopdevs Treball SCCL
License: AGPL-3
Classifier: Programming Language :: Python
Classifier: Framework :: Odoo
Classifier: Framework :: Odoo :: 16.0
Classifier: License :: OSI Approved :: GNU Affero General Public License v3
Requires-Python: >=3.10
Requires-Dist: faker
Requires-Dist: odoo-addon-component<16.1dev,>=16.0dev
Requires-Dist: odoo-addon-filmin_somconnexio<16.1dev,>=16.0dev
Requires-Dist: odoo-addon-somconnexio<16.1dev,>=16.0dev
Requires-Dist: odoo-addon-switchboard_somconnexio<16.1dev,>=16.0dev
Requires-Dist: odoo<16.1dev,>=16.0a
Requires-Dist: pyopencell==0.4.10
Dynamic: author
Dynamic: classifier
Dynamic: description
Dynamic: home-page
Dynamic: license
Dynamic: requires-dist
Dynamic: requires-python
Dynamic: summary
